{
  "toplama": {
    "title": "➕ Toplama Nasıl Yapılır?",
    "explanation": "Toplama, iki veya daha fazla sayıyı birleştirmektir. Örneğin 3 elma ile 2 elmayı bir araya getirersen, 5 elma olur. Parmaklarınızı kullanarak sayabilirsiniz.",
    "example": "🍎🍎🍎 + 🍎🍎 = 🍎🍎🍎🍎🍎 (3 + 2 = 5)\n\nAdım 1: İlk sayıyı kafandan veya parmaklarınla söyle (3)\nAdım 2: Parmaklarınla diğer sayıyı sayarak ilerle (4, 5)\nAdım 3: Toplam sonuç (5)",
    "tips": [
      "Büyük sayıdan başla, küçük sayıyı saymaya devam et",
      "Parmaklarını veya nesneleri kullan (elma, top, yıldız)",
      "Aynı cevabı birkaç kez yap, böylece hatırlamaya başlarsın",
      "Günlük hayatta toplamayı fark et: 2 kardeş + 3 arkadaş = 5 kişi"
    ]
  },
  "cikarma": {
    "title": "➖ Çıkarma Nasıl Yapılır?",
    "explanation": "Çıkarma, bir sayıdan başka bir sayıyı ayırmaktır. Örneğin 7 şekeriniz varsa ve 3 tanesini yersen, 4 tane kalır. Çıkarma, toplamanın tersidir.",
    "example": "🍬🍬🍬🍬🍬🍬🍬 - 🍬🍬🍬 = 🍬🍬🍬🍬 (7 - 3 = 4)\n\nAdım 1: Başlangıç sayısını söyle (7)\nAdım 2: Geri doğru say (6, 5, 4)\nAdım 3: Kaç kez sayıldı? (3 kez) O kadar çıkarttın\nAdım 4: Kalan sonuç (4)",
    "tips": [
      "Büyük sayıdan başla, geri doğru say",
      "Nesneler kullan ve her çıkardığında bir tane ayır",
      "Çıkarma sonucu asla negatif olmaz (0 veya daha büyük)",
      "Yakın sayılarda kolay: 10 - 9 = 1 (sadece 1 geri say)"
    ]
  },
  "carpma": {
    "title": "✖️ Çarpma Nasıl Yapılır?",
    "explanation": "Çarpma, aynı sayıyı birkaç kez toplamanın kısayoludur. 3 x 2, '3'ü iki kez topla' anlamına gelir: 3 + 3 = 6. Çarpma tablosunu öğrenmek çok önemlidir!",
    "example": "👦👦👦 x 2 = 👦👦👦👦👦👦 (3 x 2 = 3 + 3 = 6)\n\nAdım 1: İlk sayıyı söyle (3 erkek çocuk)\nAdım 2: Kaç kez var? (2 kez)\nAdım 3: Tekrar tekrar say (3 + 3)\nAdım 4: Cevap (6)",
    "tips": [
      "Toplama ile düşün: a x 2 = a + a",
      "Örneğin: 4 x 2 = 4 + 4 = 8",
      "Gruplama yap: 2 sıra, her sırada 3 çocuk = 6 çocuk",
      "Çarpım tablosunu şarkıyla veya oyunlarla öğren"
    ]
  },
  "bolme": {
    "title": "➗ Bölme Nasıl Yapılır?",
    "explanation": "Bölme, bir sayıyı eşit parçalara ayırmaktır. 8 şeker 2 çocuğa paylaştırırsan, her çocuğa 4 şeker düşer. Bölme çarpmanın tersidir.",
    "example": "🍭🍭🍭🍭🍭🍭🍭🍭 ÷ 2 = 🍭🍭🍭🍭 ve 🍭🍭🍭🍭 (8 / 2 = 4)\n\nAdım 1: Toplam sayı (8 şeker)\nAdım 2: Kaç gruba böleceği? (2 çocuk)\nAdım 3: Her gruba eşit olarak dağıt\nAdım 4: Bir grupta kaç var? (4 şeker)",
    "tips": [
      "Eşit ikiye bölersen, yarısını bul",
      "Nesneler kullan ve fiziksel olarak gruplara ayır",
      "Hangi sayı ile çarpınca toplama ulaşırız? sorusunu sor",
      "Örneğin: 10 / 2 = 5 çünkü 5 x 2 = 10"
    ]
  },
  "siralama": {
    "title": "📊 Sıralama Nasıl Yapılır?",
    "explanation": "Sıralama, sayıları küçükten büyüğe veya büyükten küçüğe düzene koymaktır. Bu, sayıları karşılaştırmanın temelidir.",
    "example": "5, 12, 3 sayılarını sırala:\nAdım 1: En küçüğü bul (3)\nAdım 2: Sonraki küçüğü bul (5)\nAdım 3: En büyüğü bul (12)\nSonuç: 3, 5, 12 (küçükten büyüğe)",
    "tips": [
      "Sayı satırını kafanda veya kağıda çiz",
      "En küçük sayı başa, en büyük sona gelir",
      "İki sayıyı karşılaştırırken: hangi sayı daha fazla nesnedir?",
      "Örneğin: 7 mi 12 mi? → 12 daha büyük → 12 seç"
    ]
  },
  "eksik_sayi": {
    "title": "❓ Eksik Sayı Nasıl Bulunur?",
    "explanation": "Eksik sayı, denklemde kayıp olan numaradır. Örneğin _ + 3 = 7'de eksik sayıyı bulmalısınız. Bu, çözüm becerilerini geliştirir.",
    "example": "_ + 3 = 7\nAdım 1: Sonuç nedir? (7)\nAdım 2: Bilinen sayı nedir? (3)\nAdım 3: 7'den 3'ü çıkar (7 - 3 = 4)\nAdım 4: Cevap 4'tür (4 + 3 = 7)\n\nProva: _ + 3 = 7 → 4 + 3 = 7 ✓",
    "tips": [
      "Sonucu ve bilinen sayıyı kullan",
      "Toplama için: eksik = sonuç - bilinen",
      "Çıkarma için: eksik = sonuç + bilinen",
      "Her zaman cevabını prova et, doğru mu kontrol et"
    ]
  }
}
